ctcsound7/__init__.py
ctcsound7/_dll.py
ctcsound7/_util.py
ctcsound7/api6.py
ctcsound7/api7.py
ctcsound7/common.py
ctcsound7/py.typed
ctcsound7-0.8.0.dist-info/METADATA
ctcsound7-0.8.0.dist-info/WHEEL
ctcsound7-0.8.0.dist-info/top_level.txt
ctcsound7-0.8.0.dist-info/RECORD
