Metadata-Version: 2.1
Name: ctcsound7
Version: 0.8.0
Summary: Python bindings to the Csound API, supporting all versions of csound higher or equal to 6.18
Author-email: Eduardo Moguillansky <eduardo.moguillansky@gmail.com>
License:                   GNU LESSER GENERAL PUBLIC LICENSE
Project-URL: Homepage, https://github.com/csound-plugins/ctcsound7
Keywords: csound
Classifier: Topic :: Multimedia :: Sound/Audio
Classifier: Programming Language :: Python :: 3
Classifier: Operating System :: OS Independent
Requires-Python: >=3.9
Requires-Dist: numpy>=2.0
